hubspyt/__init__.py
hubspyt/base_wrapper.py
hubspyt/contacts.py
hubspyt/models/__init__.py
hubspyt/models/base_model.py
hubspyt/models/contact.py
hubspyt-0.2.dist-info/DESCRIPTION.rst
hubspyt-0.2.dist-info/METADATA
hubspyt-0.2.dist-info/RECORD
hubspyt-0.2.dist-info/WHEEL
hubspyt-0.2.dist-info/metadata.json
hubspyt-0.2.dist-info/top_level.txt
