Metadata-Version: 2.0
Name: hubspyt
Version: 0.2
Summary: HubSpot API Wrapper
Home-page: https://github.com/MailValet/hubspyt
Author: Jeff Allen
Author-email: jeff.allen127@gmail.com
License: UNKNOWN
Download-URL: https://github.com/MailValet/hubspyt/archive/master.zip
Platform: UNKNOWN
Requires-Dist: requests
